random_wikipedia_article/__init__.py
random_wikipedia_article/__main__.py
random_wikipedia_article-0.1.0.dist-info/METADATA
random_wikipedia_article-0.1.0.dist-info/WHEEL
random_wikipedia_article-0.1.0.dist-info/entry_points.txt
random_wikipedia_article-0.1.0.dist-info/RECORD
